python_password_generator/python_password_generator.py
python_password_generator-0.2.dist-info/LICENSE
python_password_generator-0.2.dist-info/METADATA
python_password_generator-0.2.dist-info/WHEEL
python_password_generator-0.2.dist-info/top_level.txt
python_password_generator-0.2.dist-info/RECORD
