Metadata-Version: 2.1
Name: python-password-generator
Version: 0.2
Summary: A useful password generator
Home-page: https://github.com/commanderHR1/python-password-generator
Author: Harris Ransom
Author-email: hransom528@gmail.com
License: MIT
Platform: UNKNOWN
Classifier: License :: OSI Approved :: MIT License
Classifier: Programming Language :: Python :: 3
Classifier: Programming Language :: Python :: 3.7
